odoo/addons/partner_address_two_lines/README.rst
odoo/addons/partner_address_two_lines/__init__.py
odoo/addons/partner_address_two_lines/__manifest__.py
odoo/addons/partner_address_two_lines/i18n/it.po
odoo/addons/partner_address_two_lines/i18n/partner_address_two_lines.pot
odoo/addons/partner_address_two_lines/models/__init__.py
odoo/addons/partner_address_two_lines/models/ir_actions_report.py
odoo/addons/partner_address_two_lines/models/res_partner.py
odoo/addons/partner_address_two_lines/readme/CONTRIBUTORS.rst
odoo/addons/partner_address_two_lines/readme/DESCRIPTION.rst
odoo/addons/partner_address_two_lines/static/description/icon.png
odoo/addons/partner_address_two_lines/static/description/index.html
odoo_addon_partner_address_two_lines-16.0.1.0.0.3.dist-info/METADATA
odoo_addon_partner_address_two_lines-16.0.1.0.0.3.dist-info/WHEEL
odoo_addon_partner_address_two_lines-16.0.1.0.0.3.dist-info/top_level.txt
odoo_addon_partner_address_two_lines-16.0.1.0.0.3.dist-info/RECORD
